{
  "components.ContributeForm.company.subTitle": [
    {
      "type": 0,
      "value": "JETZT PARTNER WERDEN:"
    }
  ],
  "components.ContributeForm.company.title": [
    {
      "type": 0,
      "value": "Ich bin ein "
    },
    {
      "children": [
        {
          "type": 0,
          "value": "Unternehmen"
        }
      ],
      "type": 8,
      "value": "b"
    }
  ],
  "components.ContributeForm.developer.subTitle": [
    {
      "type": 0,
      "value": "JETZT BEITRAG LEISTEN:"
    }
  ],
  "components.ContributeForm.developer.title": [
    {
      "type": 0,
      "value": "Ich bin "
    },
    {
      "children": [
        {
          "type": 0,
          "value": "Entwickler*in"
        }
      ],
      "type": 8,
      "value": "b"
    }
  ],
  "components.ContributeForm.text": [
    {
      "type": 0,
      "value": "Ergo verfolgt "
    },
    {
      "children": [
        {
          "type": 0,
          "value": "einen offenen Ansatz"
        }
      ],
      "type": 8,
      "value": "b"
    },
    {
      "type": 0,
      "value": ", bei dem "
    },
    {
      "children": [
        {
          "type": 0,
          "value": "jeder"
        }
      ],
      "type": 8,
      "value": "b"
    },
    {
      "type": 0,
      "value": " willkommen ist, "
    },
    {
      "children": [
        {
          "type": 0,
          "value": "einen Beitrag zu leisten."
        }
      ],
      "type": 8,
      "value": "b"
    }
  ],
  "components.ContributeForm.title": [
    {
      "type": 0,
      "value": "Mitmachen"
    }
  ],
  "components.DApps.seeAllProjects": [
    {
      "type": 0,
      "value": "NOCH MEHR PROJEKTE"
    }
  ],
  "components.Sigmanauts.button": [
    {
      "type": 0,
      "value": "MEHR ERFAHREN & BEWERBEN"
    }
  ],
  "components.Sigmanauts.button.buttonContribute": [
    {
      "type": 0,
      "value": "RICHTLINIEN FÜR DIE MITARBEIT"
    }
  ],
  "components.Sigmanauts.button.discord": [
    {
      "type": 0,
      "value": "TRETE UNSEREM DISCORD BEI"
    }
  ],
  "components.Sigmanauts.button.grantsAndBounties": [
    {
      "type": 0,
      "value": "FÖRDERUNGEN & PRÄMIEN"
    }
  ],
  "components.Sigmanauts.button.writeAndReviewCode": [
    {
      "type": 0,
      "value": "TAUCHE IN ERGO EIN"
    }
  ],
  "components.Sigmanauts.formInput.button": [
    {
      "type": 0,
      "value": "ABSENDEN"
    }
  ],
  "components.Sigmanauts.formInput.email": [
    {
      "type": 0,
      "value": "E-Mail"
    }
  ],
  "components.Sigmanauts.formInput.name": [
    {
      "type": 0,
      "value": "Name / Unternehmen"
    }
  ],
  "components.Sigmanauts.formInput.text": [
    {
      "type": 0,
      "value": "Schreibe uns deine Ideen und lass uns drüber reden!"
    }
  ],
  "components.Sigmanauts.subTitle": [
    {
      "type": 0,
      "value": "Ausbildungsprogramm"
    }
  ],
  "components.Sigmanauts.text": [
    {
      "type": 0,
      "value": "Bewirb dich für das Sigmanauten-Ausbildungsprogramm, um Ergos Wachstum mitzugestalten. "
    },
    {
      "type": 1,
      "value": "br"
    },
    {
      "type": 1,
      "value": "br"
    },
    {
      "type": 0,
      "value": " Lass uns ein basisdemokratisches Grassroots-Finanzsystem erschaffen."
    }
  ],
  "components.Sigmanauts.title": [
    {
      "type": 0,
      "value": "Sigmanauten"
    }
  ],
  "components.Spotlight.button": [
    {
      "type": 0,
      "value": "ZU ALLEN BEITRÄGEN"
    }
  ],
  "components.Spotlight.title": [
    {
      "type": 0,
      "value": "Spotlight"
    }
  ],
  "components.autolykos.button": [
    {
      "type": 0,
      "value": "MINE JETZT ERG"
    }
  ],
  "components.autolykos.header": [
    {
      "type": 0,
      "value": "AUTOLYKOS"
    }
  ],
  "components.autolykos.text": [
    {
      "children": [
        {
          "type": 0,
          "value": "Autolykos"
        }
      ],
      "type": 8,
      "value": "b"
    },
    {
      "type": 0,
      "value": " ist Ergos auf GPUs ausgerichteter speicherharter, ASIC-resistenter Proof-of-Work-Algorithmus."
    }
  ],
  "components.autolykos.title": [
    {
      "type": 0,
      "value": "Die Zukunft von Proof of Work"
    }
  ],
  "components.communityHero.Discord.text": [
    {
      "type": 0,
      "value": "Treffen Sie uns auf Discord!"
    }
  ],
  "components.communityHero.Discord.title": [
    {
      "type": 0,
      "value": "Discord"
    }
  ],
  "components.communityHero.Discourse.text": [
    {
      "type": 0,
      "value": "Beteiligen Sie sich an der Diskussion im Ergo-Forum."
    }
  ],
  "components.communityHero.Discourse.title": [
    {
      "type": 0,
      "value": "Forum"
    }
  ],
  "components.communityHero.Github.text": [
    {
      "type": 0,
      "value": "Reden ist billig, hier ist der Code. 100% Open-Source."
    }
  ],
  "components.communityHero.Github.title": [
    {
      "type": 0,
      "value": "Github"
    }
  ],
  "components.communityHero.Reddit.text": [
    {
      "type": 0,
      "value": "Abonnieren Sie unsere Subreddits."
    }
  ],
  "components.communityHero.Reddit.title": [
    {
      "type": 0,
      "value": "Reddit"
    }
  ],
  "components.communityHero.Telegram.text": [
    {
      "type": 0,
      "value": "Kommen Sie auf Telegramm mit uns plaudern."
    }
  ],
  "components.communityHero.Telegram.title": [
    {
      "type": 0,
      "value": "Telegramm"
    }
  ],
  "components.communityHero.Twitter.text": [
    {
      "type": 0,
      "value": "Folgen Sie uns auf Twitter."
    }
  ],
  "components.communityHero.Twitter.title": [
    {
      "type": 0,
      "value": "Twitter"
    }
  ],
  "components.communityHero.Wiki.text": [
    {
      "type": 0,
      "value": "Ihr Community-Wiki. Tragen Sie in jeder Sprache bei!"
    }
  ],
  "components.communityHero.Wiki.title": [
    {
      "type": 0,
      "value": "Wiki"
    }
  ],
  "components.communityHero.Youtube.text": [
    {
      "type": 0,
      "value": "Abonnieren Sie für wöchentliche AMAs, ErgoPulse und mehr!"
    }
  ],
  "components.communityHero.Youtube.title": [
    {
      "type": 0,
      "value": "Youtube"
    }
  ],
  "components.communityHero.subtitle": [
    {
      "type": 0,
      "value": "GRASSROOTS FINANZEN AUS DER BASIS"
    }
  ],
  "components.communityHero.title": [
    {
      "type": 0,
      "value": "Ökosystem"
    }
  ],
  "components.communitySection.communityHero.linkText": [
    {
      "type": 0,
      "value": "Mitwirkenden"
    }
  ],
  "components.communitySection.communityHero.text1": [
    {
      "type": 0,
      "value": "Ergo ist eine dezentralisierte Basisplattform, die von ihrer Gemeinschaft angetrieben wird."
    }
  ],
  "components.communitySection.communityHero.text2": [
    {
      "type": 0,
      "value": "Treffen Sie uns auf sozialen Medien, um sich zu engagieren. Schauen Sie sich die"
    }
  ],
  "components.communitySection.communityHero.text3": [
    {
      "type": 0,
      "value": "Seite für weitere Informationen an."
    }
  ],
  "components.dApps.heading": [
    {
      "type": 0,
      "value": "DApps"
    }
  ],
  "components.discoverErgo.text.1": [
    {
      "type": 0,
      "value": "Ergo ist eine Next-Gen Proof-of-Work-Plattform mit Smart Contracts, die neue Modelle finanzieller Interaktion ermöglicht, basierend auf einer sicheren und vielseitigen Skriptsprache mit flexiblen und leistungsstarken Zero-Knowledge-Proofs (Σ-Protokolle)."
    }
  ],
  "components.discoverHero.button1": [
    {
      "type": 0,
      "value": "LIES DIE DOCS"
    }
  ],
  "components.discoverHero.button2": [
    {
      "type": 0,
      "value": "LERNE MIT DECO"
    }
  ],
  "components.discoverHero.button3": [
    {
      "type": 0,
      "value": "LIES DAS MANIFEST"
    }
  ],
  "components.discoverHero.button4": [
    {
      "type": 0,
      "value": "SCHAU INS BLOG"
    }
  ],
  "components.discoverHero.button5": [
    {
      "type": 0,
      "value": "RICHTE DICH EIN"
    }
  ],
  "components.discoverHero.button6": [
    {
      "type": 0,
      "value": "BESUCH ERGONAUT.SPACE"
    }
  ],
  "components.documents.description": [
    {
      "type": 0,
      "value": "Ergo verfolgt einen forschungsbasierten Ansatz und verwendet stabile, gut getestete Lösungen, um eine robuste Plattform für Entwickler zu bieten, auf der sie jahrelang aufbauen können. Die meisten Ergo-Lösungen sind in Papieren formalisiert, die auf Peer-Reviewed-Konferenzen vorgestellt wurden und in der Community ausgiebig diskutiert wurden."
    }
  ],
  "components.documents.heading": [
    {
      "type": 0,
      "value": "Dokumente"
    }
  ],
  "components.ecosystemHero.title": [
    {
      "type": 0,
      "value": "Ökosystem"
    }
  ],
  "components.ergoExplorer.button1": [
    {
      "type": 0,
      "value": "EXPLORER"
    }
  ],
  "components.ergoExplorer.button2": [
    {
      "type": 0,
      "value": "ERGO.WATCH"
    }
  ],
  "components.ergoRaffle.description": [
    {
      "type": 0,
      "value": "ErgoRaffle ist ein auf der Ergo-Plattform aufgebautes Crowdfunding-Service, das es jedem ermöglicht, Geld für ein Projekt zu sammeln. Dieses Projekt kann von einer direkten Spende an eine Wohltätigkeitsorganisation, einen akademischen oder Geschäftsplan oder alles Mögliche reichen, für das Sie die Menschen überzeugen können, ihre hart verdienten ERG aufzugeben! Als zusätzlichen Bonus findet nach Abschluss der Verlosung eine Lotterie statt, und ein glücklicher Teilnehmer gewinnt einen festen Prozentsatz der Verlosung als \"Verlosungsprämie\"."
    }
  ],
  "components.ergoRaffle.heading": [
    {
      "type": 0,
      "value": "Ergo Raffle"
    }
  ],
  "components.ergofoundation.list1": [
    {
      "type": 0,
      "value": "Förderung der "
    },
    {
      "children": [
        {
          "type": 0,
          "value": "störungsfreien "
        }
      ],
      "type": 8,
      "value": "b"
    },
    {
      "type": 0,
      "value": " Entwicklung des Ergo-Plattform-Protokolls"
    }
  ],
  "components.ergofoundation.list2": [
    {
      "type": 0,
      "value": "Öffentlichkeitsarbeit für die breite Akzeptanz und Nutzung der Ergo-Plattform und ihres "
    },
    {
      "children": [
        {
          "type": 0,
          "value": "nativen Tokens "
        }
      ],
      "type": 8,
      "value": "b"
    },
    {
      "type": 0,
      "value": " (ERG)"
    }
  ],
  "components.ergofoundation.list3": [
    {
      "type": 0,
      "value": "Entwicklung des "
    },
    {
      "children": [
        {
          "type": 0,
          "value": "Ökosystems "
        }
      ],
      "type": 8,
      "value": "b"
    },
    {
      "type": 0,
      "value": " rund um die Ergo-Plattform"
    }
  ],
  "components.ergofoundation.list4": [
    {
      "type": 0,
      "value": "Verbreitung der Nutzung der Ergo-Plattform und der Blockchain-Technologie für positive "
    },
    {
      "children": [
        {
          "type": 0,
          "value": "soziale Zwecke "
        }
      ],
      "type": 8,
      "value": "b"
    }
  ],
  "components.ergofoundation.list5": [
    {
      "type": 0,
      "value": "Aufrechterhaltung einer "
    },
    {
      "children": [
        {
          "type": 0,
          "value": "wirklich dezentralen Infrastruktur "
        }
      ],
      "type": 8,
      "value": "b"
    },
    {
      "type": 0,
      "value": ", und"
    }
  ],
  "components.ergofoundation.list6": [
    {
      "type": 0,
      "value": "Unterstützung der "
    },
    {
      "children": [
        {
          "type": 0,
          "value": "Privatsphäre "
        }
      ],
      "type": 8,
      "value": "b"
    },
    {
      "type": 0,
      "value": " als grundlegendes Menschenrecht."
    }
  ],
  "components.ergofoundation.title": [
    {
      "type": 0,
      "value": "Die "
    },
    {
      "children": [
        {
          "type": 0,
          "value": "Ergo-Foundation "
        }
      ],
      "type": 8,
      "value": "b"
    },
    {
      "type": 0,
      "value": " verfolgt mit Antrieb der Community folgende Ziele"
    }
  ],
  "components.exchanges.available": [
    {
      "type": 0,
      "value": "Erhältlich auf beliebten Börsen und dezentralen Börsen."
    }
  ],
  "components.exchanges.disclaimer": [
    {
      "type": 0,
      "value": "Haftungsausschluss: Börsen bieten sehr unterschiedliche Grade an Sicherheit, Datenschutz und Kontrolle über Ihre Gelder und Informationen. Wir empfehlen dringend, dass Sie Ihre eigenen Mittel aufbewahren und eine der oben genannten Brieftaschenoptionen verwenden."
    }
  ],
  "components.exchanges.heading": [
    {
      "type": 0,
      "value": "ERGO KAUFEN, VERKAUFEN UND HANDELN"
    }
  ],
  "components.exchanges.subheading": [
    {
      "type": 0,
      "value": "Börsen"
    }
  ],
  "components.explore.description": [
    {
      "type": 0,
      "value": "Der Ergo Explorer ist Ihre Schnittstelle zur Blockchain. Beobachten Sie jede Transaktion in Echtzeit. Oder sehen Sie sich von der Community kuratierte Metriken auf ergo.watch an."
    }
  ],
  "components.explore.heading": [
    {
      "type": 0,
      "value": "Erforschen"
    }
  ],
  "components.explore.subheading": [
    {
      "type": 0,
      "value": "TAUCHEN SIE IN DAS ERGO-TRANSAKTIONSMEER EIN"
    }
  ],
  "components.faq.anyQuestions": [
    {
      "type": 0,
      "value": "FRAGEN?"
    }
  ],
  "components.faq.description": [
    {
      "type": 0,
      "value": "Wir haben einige der am häufigsten gestellten Fragen zusammengestellt."
    }
  ],
  "components.faq.heading": [
    {
      "type": 0,
      "value": "Häufig gestellte Fragen"
    }
  ],
  "components.faq.text.2": [
    {
      "type": 0,
      "value": "DU FINDEST NICHT, "
    },
    {
      "type": 1,
      "value": "breakingLine"
    },
    {
      "type": 0,
      "value": " WONACH DU SUCHST?"
    }
  ],
  "components.favorites.button1": [
    {
      "type": 0,
      "value": "ERKUNDE ERGO RAFFLE"
    }
  ],
  "components.getErg.BuyIt.text": [
    {
      "type": 0,
      "value": "Erhältlich auf beliebten zentralisierten und dezentralisierten Börsen."
    }
  ],
  "components.getErg.BuyIt.title": [
    {
      "type": 0,
      "value": "Börsen"
    }
  ],
  "components.getErg.MineIt.text": [
    {
      "type": 0,
      "value": "Autolykos, ein ASIC-resistenter und fairer Proof-of-Work-Algorithmus, der für gängige GPUs geeignet ist."
    }
  ],
  "components.getErg.MineIt.title": [
    {
      "type": 0,
      "value": "Abbau"
    }
  ],
  "components.getErg.StoreIt.text": [
    {
      "type": 0,
      "value": "Einfache und sichere nicht-kustodiale Brieftaschen, um Ihre ERG sicher aufzubewahren."
    }
  ],
  "components.getErg.StoreIt.title": [
    {
      "type": 0,
      "value": "Brieftaschen"
    }
  ],
  "components.getErg.UseIt.title": [
    {
      "type": 0,
      "value": "Setzen Sie Ihr ERG heute in unserem wachsenden Ökosystem ein."
    }
  ],
  "components.getErg.description": [
    {
      "type": 0,
      "value": "Es entsteht ein reiches Ökosystem auf der Basis von Ergo. Egal, ob Sie ein Entwickler, ein Bergmann oder ein Investor sind - wir haben Sie abgedeckt."
    }
  ],
  "components.getErg.heroTitle": [
    {
      "type": 0,
      "value": "UNAUFHALTBARES DEFI"
    }
  ],
  "components.getErg.title": [
    {
      "type": 0,
      "value": "ERG erhalten"
    }
  ],
  "components.grantsAndBounties.button1": [
    {
      "type": 0,
      "value": "PRÄMIEN"
    }
  ],
  "components.grantsAndBounties.button2": [
    {
      "type": 0,
      "value": "STARTE EIN RAFFLE"
    }
  ],
  "components.grantsAndBounties.button3": [
    {
      "type": 0,
      "value": "KONTAKTIERE UNS"
    }
  ],
  "components.grantsAndBounties.description": [
    {
      "type": 0,
      "value": "Im Allgemeinen unterliegt alles, was für die Gemeinschaft lehrreich ist, einer Prämie, auch wenn es nicht ausdrücklich aufgeführt ist. Wir suchen nach Zuschüssen für Projekte, die sich auf den Aufbau wichtiger Infrastrukturen im Ökosystem konzentrieren. Der schnellste Weg, um eine Finanzierung zu erhalten, besteht jedoch darin, eine Verlosung zu starten."
    }
  ],
  "components.grantsAndBounties.heading": [
    {
      "type": 0,
      "value": "Zuschüsse und Prämien"
    }
  ],
  "components.hallOfFame.description1": [
    {
      "type": 0,
      "value": "Ergo wurde von einem Team gegründet, das über einen umfassenden Hintergrund in der Core-Entwicklung mit Kryptowährungen und Blockchain-Frameworks wie NXT, Scorex, Cardano und Waves verfügt. Im Folgenden findest Du kurze Biografien einiger Mitglieder des Ergo-Core-Teams sowie einiger der vielen anderen beteiligten Entwickler*innen und Community-Mitglieder, von denen einige anonym an der Entwicklung teilnehmen."
    }
  ],
  "components.hallOfFame.description2": [
    {
      "type": 0,
      "value": "Ergo ist basisorientiert, und die meisten Mitglieder des Core-Teams (und sogar der Foundation) haben als Mitglieder der Community begonnen. Eine kurze Beschreibung sowie weitere Angaben zur Ergo Foundation findest Du weiter unten."
    }
  ],
  "components.hallOfFame.tab1": [
    {
      "type": 0,
      "value": "CORE"
    }
  ],
  "components.hallOfFame.tab2": [
    {
      "type": 0,
      "value": "COMMUNITY"
    }
  ],
  "components.hallOfFame.tab3": [
    {
      "type": 0,
      "value": "FOUNDATION"
    }
  ],
  "components.hallOfFame.title": [
    {
      "type": 0,
      "value": "Hall Of Fame"
    }
  ],
  "components.highlights.slide.1.quote": [
    {
      "type": 0,
      "value": "95,57% "
    },
    {
      "type": 1,
      "value": "breakingLine"
    },
    {
      "type": 0,
      "value": "Öffentliche Zuteilung"
    }
  ],
  "components.highlights.slide.1.text": [
    {
      "type": 0,
      "value": "Als Ergo 2019 gestartet wurde, gab es kein Initial Coin Offering, kein Pre-Mine und keine Vorab-Zuteilung von Token an Teammitglieder oder Risikokapitalgeber. Ein wirklich fairer Start mit 4,43% der Mittel für die Entwicklung des Ökosystems. Unübertroffen in jeder anderen Smart-Contract-Plattform."
    }
  ],
  "components.highlights.slide.1.title": [
    {
      "type": 0,
      "value": "Ein Fairer Start"
    }
  ],
  "components.highlights.slide.2.quote": [
    {
      "type": 0,
      "value": "TRUE P2P"
    }
  ],
  "components.highlights.slide.2.text": [
    {
      "type": 0,
      "value": "Ermöglicht mehr innovative, gezielte Umsetzungen, die herkömmliche Banken nicht erreichen können. Ergo bietet leistungsstarke Tools mit Smart-Contract-basierten Mikrokredit-Einrichtungen und Local Exchange Trading Systems (LETS)."
    }
  ],
  "components.highlights.slide.2.title": [
    {
      "type": 0,
      "value": "Alternative Ökonomie"
    }
  ],
  "components.highlights.slide.3.quote": [
    {
      "type": 0,
      "value": "Σ-Protokolle"
    }
  ],
  "components.highlights.slide.3.text": [
    {
      "type": 0,
      "value": "Datenschutz muss eine Option bleiben, um die Autonomie zu schützen. Privatsphäre bedeutet die Fähigkeit, Barrieren zu schaffen und Grenzen zu errichten, um einen Raum für das Individuum zu schaffen. Es liegt an jedem Einzelnen, welche Grenzen und Barrieren er wählt. Dies ermöglicht neue Modelle der finanziellen Interaktion, unterstützt durch eine sichere und reichhaltige Skriptsprache, ErgoScript, und flexible und leistungsstarke Zero-Knowledge-Beweise."
    }
  ],
  "components.highlights.slide.3.title": [
    {
      "type": 0,
      "value": "Optionale Privatsphäre"
    }
  ],
  "components.highlights.title": [
    {
      "type": 0,
      "value": "HIGHLIGHTS"
    }
  ],
  "components.homeHero.button": [
    {
      "type": 0,
      "value": "TAUCHE EIN"
    }
  ],
  "components.homeHero.text": [
    {
      "type": 0,
      "value": "Ergo ist eine Next-Gen Proof-of-Work-Plattform mit Smart Contracts, die durch sichere, zugängliche und dezentralisierte Finanztools die wirtschaftliche Freiheit einfacher Menschen gewährleistet."
    }
  ],
  "components.homeHero.title": [
    {
      "type": 0,
      "value": "Energie für die Zukunft der Finanzen"
    }
  ],
  "components.homeInfo.blockReward": [
    {
      "type": 0,
      "value": "BLOCKBELOHNUNG"
    }
  ],
  "components.homeInfo.circulatingSupply": [
    {
      "type": 0,
      "value": "ERG IM UMLAUF"
    }
  ],
  "components.homeInfo.hashRate": [
    {
      "type": 0,
      "value": "HASHRATE"
    }
  ],
  "components.homeInfo.transactionPerDay": [
    {
      "type": 0,
      "value": "TRANSAKTIONEN PRO TAG"
    }
  ],
  "components.learn.description": [
    {
      "type": 0,
      "value": "Beginnen Sie mit den Grundlagen. Was ist Ergo? Was können Sie auf Ergo tun?"
    }
  ],
  "components.learn.heading": [
    {
      "type": 0,
      "value": "Lernen"
    }
  ],
  "components.mining.button1": [
    {
      "type": 0,
      "value": "Dokumentation"
    }
  ],
  "components.mining.button2": [
    {
      "type": 0,
      "value": "Mining-Pool-Statistiken"
    }
  ],
  "components.mining.button3": [
    {
      "type": 0,
      "value": "Discord"
    }
  ],
  "components.mining.button4": [
    {
      "type": 0,
      "value": "Subreddit"
    }
  ],
  "components.mining.button5": [
    {
      "type": 0,
      "value": "Mining-Blog-Posts"
    }
  ],
  "components.mining.calculator.currentBlockReward": [
    {
      "type": 0,
      "value": "Aktuelle Blockbelohnung"
    }
  ],
  "components.mining.calculator.currentPrice": [
    {
      "type": 0,
      "value": "Aktueller Preis"
    }
  ],
  "components.mining.calculator.description": [
    {
      "type": 0,
      "value": "Autolykos ist der zugrunde liegende memory-hard ASIC-resistente Proof of Work (PoW)-Algorithmus, der auf GPUs ausgerichtet ist."
    }
  ],
  "components.mining.calculator.networkHashrate": [
    {
      "type": 0,
      "value": "Netzwerk-Hashrate"
    }
  ],
  "components.mining.calculator.rev": [
    {
      "type": 0,
      "value": "Tägliche Einnahmen"
    }
  ],
  "components.mining.calculator.title": [
    {
      "type": 0,
      "value": "Mining-Rechner"
    }
  ],
  "components.mining.minersTitle": [
    {
      "type": 0,
      "value": "Bergleute"
    }
  ],
  "components.mining.miningPoolsTitle": [
    {
      "type": 0,
      "value": "Mining-Pools"
    }
  ],
  "components.mining.text.1": [
    {
      "type": 0,
      "value": "Ergos Mining basiert auf Autolykos, einem in Scala programmierten, ASIC-resistenten Proof-of-Work-Algorithmus. Er kann auf den meisten Low-End-GPUs bei vergleichsweise niedrigeren Temperaturen laufen und holt dadurch mehr Lebenszeit aus der Hardware. In Kombination mit dem eUTXO-Modell und der Off-Chain-Auslagerung von größeren Rechenoperationen entsteht so ein äußerst effizientes Proof-of-Work."
    }
  ],
  "components.mining.text.2": [
    {
      "type": 0,
      "value": "Willkommen in der Zukunft von Proof-of-Work."
    }
  ],
  "components.mining.text.3": [
    {
      "type": 0,
      "value": "Um loszulegen, schau ins Mining-Handbuch der Community oder trete den Mining-Diskussionskanälen bei."
    }
  ],
  "components.mining.title": [
    {
      "type": 0,
      "value": "Mining"
    }
  ],
  "components.news.blog": [
    {
      "type": 0,
      "value": "Blog"
    }
  ],
  "components.news.latest": [
    {
      "type": 0,
      "value": "Aktuelle News"
    }
  ],
  "components.news.title": [
    {
      "type": 0,
      "value": "News"
    }
  ],
  "components.ourFavorites.heading": [
    {
      "type": 0,
      "value": "UNSERE FAVORITEN"
    }
  ],
  "components.ourmission.description": [
    {
      "type": 0,
      "value": "Die Ergo Foundation hat sich zu einer organischen und störungsfreien Entwicklung des Ergo-Platform-Protokolls verpflichtet."
    }
  ],
  "components.ourmission.emissionAndTokenomics": [
    {
      "type": 0,
      "value": "AUSSCHÜTTUNG UND TOKENOMICS"
    }
  ],
  "components.ourmission.ergofoundation": [
    {
      "type": 0,
      "value": "DIE ERGO FOUNDATION"
    }
  ],
  "components.ourmission.reachus.twitter": [
    {
      "type": 0,
      "value": "ERREICHE UNS BEI TWITTER"
    }
  ],
  "components.ourmission.subdescription": [
    {
      "type": 0,
      "value": "Die Ergo Foundation ist bestrebt, die Anzahl der wertvollen Ökosystementwicklungen zu erhöhen, die auf Open-Source-Basis mit einer möglichst permissiven Lizenz durchgeführt werden."
    }
  ],
  "components.ourmission.title": [
    {
      "type": 0,
      "value": "Unsere Mission"
    }
  ],
  "components.partners.title": [
    {
      "type": 0,
      "value": "Partner"
    }
  ],
  "components.roadmap.coinmarketcal": [
    {
      "type": 0,
      "value": "MEHR INFOS AUF COINMARKETCAL"
    }
  ],
  "components.roadmap.description": [
    {
      "type": 0,
      "value": "Bitte beachte, dass Ergo eine offene Plattform ist. Viele der unten aufgeführten Projekte haben keine formale Verbindung zur Ergo Foundation oder zueinander."
    }
  ],
  "components.roadmap.section1.title": [
    {
      "type": 0,
      "value": "BISHER"
    }
  ],
  "components.roadmap.section2.title": [
    {
      "type": 0,
      "value": "ÖKOSYSTEM"
    }
  ],
  "components.roadmap.section3.title": [
    {
      "type": 0,
      "value": "BALD"
    }
  ],
  "components.roadmap.section4.title": [
    {
      "type": 0,
      "value": "2024 & DANACH"
    }
  ],
  "components.roadmap.title": [
    {
      "type": 0,
      "value": "Roadmap"
    }
  ],
  "components.software.description": [
    {
      "type": 0,
      "value": "Der Ergo-Knoten ist Ihr Einstieg in die Entwicklung auf Ergo und ermöglicht die Kommunikation mit der Blockchain."
    }
  ],
  "components.software.heading": [
    {
      "type": 0,
      "value": "Software"
    }
  ],
  "components.uniqueErgo.card1.button": [
    {
      "type": 0,
      "value": "MEHR INFOS"
    }
  ],
  "components.uniqueErgo.card1.text": [
    {
      "type": 0,
      "value": "Ergo stützt sich auf zehn Jahre Blockchain-Entwicklung und ergänzt bewährte Prinzipien mit der besten von Expert*innen begutachteten akademischen Forschung zu Kryptografie, Konsensmodellen und digitalen Währungen. Wir beginnen mit robusten Blockchain-Grundlagen und implementieren neue und leistungsstarke Kryptografie auf nativer Basis."
    }
  ],
  "components.uniqueErgo.card1.title": [
    {
      "type": 0,
      "value": "FORSCHUNGSBASIERT MIT REAL-WORLD-FOKUS"
    }
  ],
  "components.uniqueErgo.card2.button": [
    {
      "type": 0,
      "value": "MEHR INFOS"
    }
  ],
  "components.uniqueErgo.card2.text": [
    {
      "type": 0,
      "value": "Ergo bietet ausgezeichnete Unterstützung für wirtschaftliche Verträge in der realen Welt. Ergo unterstützt vielseitige dApps, die berechenbar und mit bekannten Kosten ausgeführt werden und keine der Gefahren uneingeschränkter Funktionalität aufweisen. Die Smart Contracts von Ergo ermöglichen es, weitreichende Aufgaben auszuführen und können Turing-vollständig sein, doch wir wissen immer im Voraus, wie viel der Code kosten wird und ob er erfolgreich laufen wird."
    }
  ],
  "components.uniqueErgo.card2.title": [
    {
      "type": 0,
      "value": "MÄCHTIG UND SICHER"
    }
  ],
  "components.uniqueErgo.card3.button": [
    {
      "type": 0,
      "value": "MEHR INFOS"
    }
  ],
  "components.uniqueErgo.card3.text": [
    {
      "type": 0,
      "value": "Sigma-Protokolle sind die Grundlage für die Smart Contracts von Ergo. Sie ermöglichen eine Reihe effizienter Zero-Knowledge-Protokolle, die es uns ermöglichen, Dinge zu implementieren, die sonst entweder unmöglich oder aber riskant und teuer wären. Dies ermöglicht eine souveräne Privatsphäre auf Anwendungsebene: vertrauenslose Skripte, die für den Zugriff auf Mixer oder andere Funktionen verwendet werden können - ohne dass Dritte erforderlich sind."
    }
  ],
  "components.uniqueErgo.card3.title": [
    {
      "type": 0,
      "value": "INTELLIGENT UND EINGÄNGIG"
    }
  ],
  "components.uniqueErgo.card4.button": [
    {
      "type": 0,
      "value": "MEHR INFOS"
    }
  ],
  "components.uniqueErgo.card4.text": [
    {
      "type": 0,
      "value": "Wir finden, dass normale Nutzer*innen, die keinen vollständigen Node betreiben, die gleichen Sicherheitsvorteile genießen sollten wie Miner*innen. Ergos nicht-interaktives Proof-of-Proof-of-Work (NiPoPoW) ermöglicht es allen, Transaktionen mit vollem Vertrauen durchzuführen und zu verifizieren, ohne den Speicherplatz, die Bandbreite und die Zeit für das Herunterladen der vollständigen Blockchain zu benötigen. Tatsächlich ist nur 1 MB an Daten erforderlich - das bedeutet, dass ein beliebiges Endgerät verwendet werden kann."
    }
  ],
  "components.uniqueErgo.card4.title": [
    {
      "type": 0,
      "value": "SICHER UND ZUGÄNGLICH"
    }
  ],
  "components.uniqueErgo.title": [
    {
      "type": 0,
      "value": "WAS MACHT ERGO EINZIGARTIG"
    }
  ],
  "components.usingErg.BuyIt.text": [
    {
      "type": 0,
      "value": "Erhältlich auf beliebten zentralisierten und dezentralisierten Börsen."
    }
  ],
  "components.usingErg.BuyIt.title": [
    {
      "type": 0,
      "value": "Börsen"
    }
  ],
  "components.usingErg.MineIt.text": [
    {
      "type": 0,
      "value": "Autolykos, ein ASIC-resistenter und fairer Proof-of-Work-Algorithmus, der für gängige GPUs geeignet ist."
    }
  ],
  "components.usingErg.MineIt.title": [
    {
      "type": 0,
      "value": "Abbau"
    }
  ],
  "components.usingErg.StoreIt.text": [
    {
      "type": 0,
      "value": "Einfache und sichere nicht-betreute Geldbörsen, um Ihre ERG sicher aufzubewahren."
    }
  ],
  "components.usingErg.StoreIt.title": [
    {
      "type": 0,
      "value": "Brieftaschen"
    }
  ],
  "components.usingErg.UseIt.title": [
    {
      "type": 0,
      "value": "Nutzen Sie heute Ihre ERG in unserem wachsenden Ökosystem."
    }
  ],
  "components.usingErg.description": [
    {
      "type": 0,
      "value": "Auf Ergo ist ein reichhaltiges Ökosystem entstanden. Ob Du Entwickler*in, Miner*in oder Investor*in bist - wir haben alles für Dich."
    }
  ],
  "components.usingErg.subtitle": [
    {
      "type": 0,
      "value": "UNAUFHALTSAME DEFI"
    }
  ],
  "components.usingErg.title": [
    {
      "type": 0,
      "value": "HOL DIR ERG"
    }
  ],
  "components.wallets.chooseYours": [
    {
      "type": 0,
      "value": "WÄHLEN SIE IHRES"
    }
  ],
  "components.wallets.coldStorageHeader": [
    {
      "type": 0,
      "value": "Kaltspeicherung"
    }
  ],
  "components.wallets.featureHeader": [
    {
      "type": 0,
      "value": "Feature"
    }
  ],
  "components.wallets.hotStorageHeader": [
    {
      "type": 0,
      "value": "Heißlagerung"
    }
  ],
  "components.wallets.mobileAppHeader": [
    {
      "type": 0,
      "value": "Mobile App"
    }
  ],
  "components.wallets.setupGuides": [
    {
      "type": 0,
      "value": "SETUP-ANLEITUNGEN"
    }
  ],
  "components.wallets.walletDescription1": [
    {
      "type": 0,
      "value": "Digitale Brieftaschen können dazu beitragen, Ihre digitale Währung sicher, privat und unter Ihrer Kontrolle zu halten."
    }
  ],
  "components.wallets.walletDescription2": [
    {
      "type": 0,
      "value": "Beachten Sie, dass Brieftaschen von Drittanbietern unterstützt werden. Wir stellen die unten aufgeführten Informationen nur als Höflichkeit zur Verfügung, um das gesamte Erlebnis mit digitalen Währungen für Sie zu vereinfachen."
    }
  ],
  "components.wallets.walletsHeader": [
    {
      "type": 0,
      "value": "Brieftaschen"
    }
  ],
  "components.wallets.walletsTitle": [
    {
      "type": 0,
      "value": "Brieftaschen"
    }
  ],
  "components.wiki.description": [
    {
      "type": 0,
      "value": "ergonaut.space ist unser von der Community betriebenes Wiki! Randvoll mit vielen großartigen Informationen zu den zugrunde liegenden technischen Details der Ergo-Blockchain in einer leicht verständlichen Sprache für nicht-technische Personen. Es gibt auch viele Anleitungen, Tutorials und von Benutzern eingereichte Inhalte. Erstellen Sie ein Konto, um beizutragen!"
    }
  ],
  "components.wiki.description.short": [
    {
      "type": 0,
      "value": "ergonaut.space ist das Community-Wiki der Ergo-Blockchain, ein Leitfaden, der erklärt, wie man die Ergo-Blockchain verwendet und die zugrunde liegenden technischen Details in einer leicht verständlichen Sprache für nicht-technische Personen übersetzt."
    }
  ],
  "components.wiki.heading": [
    {
      "type": 0,
      "value": "Wiki"
    }
  ],
  "footer.blog.title": [
    {
      "type": 0,
      "value": "BLOG"
    }
  ],
  "footer.community.1": [
    {
      "type": 0,
      "value": "Trete unseren Kanälen bei"
    }
  ],
  "footer.community.2": [
    {
      "type": 0,
      "value": "Sigmanauten"
    }
  ],
  "footer.community.3": [
    {
      "type": 0,
      "value": "Bei Ergo mitmachen"
    }
  ],
  "footer.community.4": [
    {
      "type": 0,
      "value": "Hall of Fame"
    }
  ],
  "footer.community.5": [
    {
      "type": 0,
      "value": "Ergo Foundation"
    }
  ],
  "footer.community.title": [
    {
      "type": 0,
      "value": "COMMUNITY"
    }
  ],
  "footer.discover.1": [
    {
      "type": 0,
      "value": "Software Releases"
    }
  ],
  "footer.discover.2": [
    {
      "type": 0,
      "value": "Förderungen & Prämien"
    }
  ],
  "footer.discover.3": [
    {
      "type": 0,
      "value": "FAQ"
    }
  ],
  "footer.discover.4": [
    {
      "type": 0,
      "value": "Explorer"
    }
  ],
  "footer.discover.5": [
    {
      "type": 0,
      "value": "Dokumente"
    }
  ],
  "footer.discover.title": [
    {
      "type": 0,
      "value": "ENTDECKEN"
    }
  ],
  "footer.ecosystem.1": [
    {
      "type": 0,
      "value": "DApps"
    }
  ],
  "footer.ecosystem.2": [
    {
      "type": 0,
      "value": "Roadmap"
    }
  ],
  "footer.ecosystem.3": [
    {
      "type": 0,
      "value": "Wiki"
    }
  ],
  "footer.ecosystem.4": [
    {
      "type": 0,
      "value": "Ergo Raffle"
    }
  ],
  "footer.ecosystem.5": [
    {
      "type": 0,
      "value": "Videocasts"
    }
  ],
  "footer.ecosystem.title": [
    {
      "type": 0,
      "value": "ÖKOSYSTEM"
    }
  ],
  "footer.getErg.1": [
    {
      "type": 0,
      "value": "Minen"
    }
  ],
  "footer.getErg.2": [
    {
      "type": 0,
      "value": "Mining Rechner"
    }
  ],
  "footer.getErg.3": [
    {
      "type": 0,
      "value": "Wallets"
    }
  ],
  "footer.getErg.4": [
    {
      "type": 0,
      "value": "Exchanges/Börsen"
    }
  ],
  "footer.getErg.title": [
    {
      "type": 0,
      "value": "HOL DIR ERG"
    }
  ],
  "footer.legal": [
    {
      "type": 0,
      "value": "Rechtliches"
    }
  ],
  "footer.news.title": [
    {
      "type": 0,
      "value": "NEWS"
    }
  ],
  "footer.privacyPolicy": [
    {
      "type": 0,
      "value": "Datenschutzhinweise"
    }
  ],
  "footer.weGotIt": [
    {
      "type": 0,
      "value": "We got it!"
    }
  ],
  "navigation.discover": [
    {
      "type": 0,
      "value": "ENTDECKEN"
    }
  ],
  "navigation.ecosystem": [
    {
      "type": 0,
      "value": "ÖKOSYSTEM"
    }
  ],
  "navigation.ergoCommunity": [
    {
      "type": 0,
      "value": "ERGO COMMUNITY"
    }
  ],
  "navigation.getErg": [
    {
      "type": 0,
      "value": "HOL DIR ERG"
    }
  ],
  "navigation.moreContent": [
    {
      "type": 0,
      "value": "Mehr Inhalte?"
    }
  ],
  "pages.404.hero": [
    {
      "type": 0,
      "value": "404. Seite nicht gefunden."
    }
  ],
  "pages.404.title": [
    {
      "type": 0,
      "value": "Nicht gefunden"
    }
  ],
  "pages.blog.title": [
    {
      "type": 0,
      "value": "Blog"
    }
  ],
  "pages.community.title": [
    {
      "type": 0,
      "value": "Community"
    }
  ],
  "pages.discover.title": [
    {
      "type": 0,
      "value": "Entdecken"
    }
  ],
  "pages.ecosystem.title": [
    {
      "type": 0,
      "value": "Ökosystem"
    }
  ],
  "pages.get-erg.title": [
    {
      "type": 0,
      "value": "Hol dir Erg"
    }
  ],
  "pages.home.title": [
    {
      "type": 0,
      "value": "Home"
    }
  ],
  "pages.legal.title": [
    {
      "type": 0,
      "value": "Rechtliches"
    }
  ],
  "pages.mobile-wallets": [
    {
      "type": 0,
      "value": "Mobile Wallets"
    }
  ],
  "pages.privacyPolicy.title": [
    {
      "type": 0,
      "value": "Datenschutzrichtlinie"
    }
  ]
}