{
  "components.ContributeForm.company.subTitle": [
    {
      "type": 0,
      "value": "ХОТИТЕ СТАТЬ ПАРТНЕРОМ?"
    }
  ],
  "components.ContributeForm.company.title": [
    {
      "type": 0,
      "value": "Я представитель "
    },
    {
      "children": [
        {
          "type": 0,
          "value": "компании"
        }
      ],
      "type": 8,
      "value": "b"
    }
  ],
  "components.ContributeForm.developer.subTitle": [
    {
      "type": 0,
      "value": "ЧЕМ Я МОГУ ПОМОЧЬ?"
    }
  ],
  "components.ContributeForm.developer.title": [
    {
      "type": 0,
      "value": "Я "
    },
    {
      "children": [
        {
          "type": 0,
          "value": "разработчик"
        }
      ],
      "type": 8,
      "value": "b"
    }
  ],
  "components.ContributeForm.text": [
    {
      "type": 0,
      "value": "Мы открыты для сотрудничества, "
    },
    {
      "children": [
        {
          "type": 0,
          "value": "любой может внести свой вклад."
        }
      ],
      "type": 8,
      "value": "b"
    }
  ],
  "components.ContributeForm.title": [
    {
      "type": 0,
      "value": "Сотрудничество"
    }
  ],
  "components.DApps.seeAllProjects": [
    {
      "type": 0,
      "value": "ПОСМОТРЕТЬ ВСЕ ПРОЕКТЫ"
    }
  ],
  "components.Sigmanauts.button": [
    {
      "type": 0,
      "value": "УЗНАТЬ БОЛЬШЕ & ЗАПИСАТЬСЯ"
    }
  ],
  "components.Sigmanauts.button.buttonContribute": [
    {
      "type": 0,
      "value": "ПРАВИЛА СОТРУДНИЧЕСТВА"
    }
  ],
  "components.Sigmanauts.button.discord": [
    {
      "type": 0,
      "value": "ПРИСОЕДИНИТЕСЬ К НАМ В DISCORD"
    }
  ],
  "components.Sigmanauts.button.grantsAndBounties": [
    {
      "type": 0,
      "value": "ГРАНТЫ & НАГРАДЫ"
    }
  ],
  "components.Sigmanauts.button.writeAndReviewCode": [
    {
      "type": 0,
      "value": "ПОГРУЖЕНИЕ В ERGO"
    }
  ],
  "components.Sigmanauts.formInput.button": [
    {
      "type": 0,
      "value": "ОТПРАВИТЬ"
    }
  ],
  "components.Sigmanauts.formInput.email": [
    {
      "type": 0,
      "value": "E-Mail"
    }
  ],
  "components.Sigmanauts.formInput.name": [
    {
      "type": 0,
      "value": "Имя / Компания"
    }
  ],
  "components.Sigmanauts.formInput.text": [
    {
      "type": 0,
      "value": "Пишите нам ваши предложения и идеи, обсудим!"
    }
  ],
  "components.Sigmanauts.subTitle": [
    {
      "type": 0,
      "value": "Программа обучения"
    }
  ],
  "components.Sigmanauts.text": [
    {
      "type": 0,
      "value": "Подайте заявку на участие в программе обучения Сигманавтов, чтобы помочь формировать и развивать Ergo. "
    },
    {
      "type": 1,
      "value": "br"
    },
    {
      "type": 1,
      "value": "br"
    },
    {
      "type": 0,
      "value": " Создайте основу финансов будущего."
    }
  ],
  "components.Sigmanauts.title": [
    {
      "type": 0,
      "value": "Сигманавты"
    }
  ],
  "components.Spotlight.button": [
    {
      "type": 0,
      "value": "ПОСМОТРЕТЬ ВСЕ ЗАПИСИ"
    }
  ],
  "components.Spotlight.title": [
    {
      "type": 0,
      "value": "В центре внимания"
    }
  ],
  "components.autolykos.button": [
    {
      "type": 0,
      "value": "Майнинг ERGO"
    }
  ],
  "components.autolykos.header": [
    {
      "type": 0,
      "value": "AUTOLYKOS"
    }
  ],
  "components.autolykos.text": [
    {
      "children": [
        {
          "type": 0,
          "value": "Autolykos"
        }
      ],
      "type": 8,
      "value": "b"
    },
    {
      "type": 0,
      "value": " это, основанный на принципе «Доказательтве выполнения работы» (Proof of Work), алгоритм, требовательный к памяти, устойчивый к майнингу на ASIC и ориентированный на графические ускорители."
    }
  ],
  "components.autolykos.title": [
    {
      "type": 0,
      "value": "Будущее принципа «Доказательство выполнения работы» (Proof of Work)"
    }
  ],
  "components.communityHero.Discord.text": [
    {
      "type": 0,
      "value": "Присоединяйтесь к нам в Discord!"
    }
  ],
  "components.communityHero.Discord.title": [
    {
      "type": 0,
      "value": "Discord"
    }
  ],
  "components.communityHero.Discourse.text": [
    {
      "type": 0,
      "value": "Присоединяйтесь к обсуждению на форуме Ergo."
    }
  ],
  "components.communityHero.Discourse.title": [
    {
      "type": 0,
      "value": "Форум"
    }
  ],
  "components.communityHero.Github.text": [
    {
      "type": 0,
      "value": "Действия важнее слов. 100% Открытый код."
    }
  ],
  "components.communityHero.Github.title": [
    {
      "type": 0,
      "value": "Github"
    }
  ],
  "components.communityHero.Reddit.text": [
    {
      "type": 0,
      "value": "Подпишитесь на наши сабреддиты."
    }
  ],
  "components.communityHero.Reddit.title": [
    {
      "type": 0,
      "value": "Reddit"
    }
  ],
  "components.communityHero.Telegram.text": [
    {
      "type": 0,
      "value": "Присоединяйтесь к нам в Telegram для общения."
    }
  ],
  "components.communityHero.Telegram.title": [
    {
      "type": 0,
      "value": "Telegram"
    }
  ],
  "components.communityHero.Twitter.text": [
    {
      "type": 0,
      "value": "Подписывайтесь на наш Twitter."
    }
  ],
  "components.communityHero.Twitter.title": [
    {
      "type": 0,
      "value": "Twitter"
    }
  ],
  "components.communityHero.Wiki.text": [
    {
      "type": 0,
      "value": "Ваша вики сообщества. Внесите свой вклад на любом языке!"
    }
  ],
  "components.communityHero.Wiki.title": [
    {
      "type": 0,
      "value": "Вики"
    }
  ],
  "components.communityHero.Youtube.text": [
    {
      "type": 0,
      "value": "Подписывайтесь на наш Youtube канал для еженедельных AMAs, ErgoPulse и многое другое!"
    }
  ],
  "components.communityHero.Youtube.title": [
    {
      "type": 0,
      "value": "Youtube"
    }
  ],
  "components.communityHero.subtitle": [
    {
      "type": 0,
      "value": "ОСНОВА ФИНАНСОВ БУДУЩЕГО"
    }
  ],
  "components.communityHero.title": [
    {
      "type": 0,
      "value": "Экосистема"
    }
  ],
  "components.communitySection.communityHero.linkText": [
    {
      "type": 0,
      "value": "Участие"
    }
  ],
  "components.communitySection.communityHero.text1": [
    {
      "type": 0,
      "value": "Ergo - это децентрализованная платформа, созданная и поддерживаемая своим сообществом. "
    }
  ],
  "components.communitySection.communityHero.text2": [
    {
      "type": 0,
      "value": "Присоединяйтесь к нам в социальных сетях, чтобы стать частью сообщества. Обязательно ознакомьтесь с разделом "
    }
  ],
  "components.communitySection.communityHero.text3": [
    {
      "type": 0,
      "value": ", чтобы узнать больше информации."
    }
  ],
  "components.dApps.heading": [
    {
      "type": 0,
      "value": "DApps"
    }
  ],
  "components.discoverErgo.text.1": [
    {
      "type": 0,
      "value": "Ergo — это платформа смарт-контрактов следующего поколения, построенная на принципе «Доказательтве выполнения работы» (Proof of Work), которая позволяет использовать новые модели финансового взаимодействия, основанные на безопасном и богатом языке сценариев, построенном с гибкими и мощными доказательствами с нулевым разглашением (Σ-протоколы)."
    }
  ],
  "components.discoverHero.button1": [
    {
      "type": 0,
      "value": "ПРОЧИТАТЬ ДОКУМЕНТАЦИЮ"
    }
  ],
  "components.discoverHero.button2": [
    {
      "type": 0,
      "value": "ВИДЕО-ОБУЧЕНИЕ С DECO"
    }
  ],
  "components.discoverHero.button3": [
    {
      "type": 0,
      "value": "ИЗУЧИТЬ МАНИФЕСТ"
    }
  ],
  "components.discoverHero.button4": [
    {
      "type": 0,
      "value": "ПОСМОТРЕТЬ В БЛОГЕ"
    }
  ],
  "components.discoverHero.button5": [
    {
      "type": 0,
      "value": "КАК УСТАНОВИТЬ"
    }
  ],
  "components.discoverHero.button6": [
    {
      "type": 0,
      "value": "ПОСЕТИТЬ ERGONAUT.SPACE"
    }
  ],
  "components.discoverHero.title": [
    {
      "type": 0,
      "value": "Откройте для себя Ergo"
    }
  ],
  "components.documents.description": [
    {
      "type": 0,
      "value": "Ergo подходит к своей платформе на основе исследований и использует стабильные, хорошо проверенные решения для создания прочной платформы для разработчиков, чтобы они могли строить на этом годами. Большинство решений Ergo формализованы в статьях, представленных на научно-практических конференциях и были широко обсуждены в сообществе."
    }
  ],
  "components.documents.heading": [
    {
      "type": 0,
      "value": "Документы"
    }
  ],
  "components.ecosystemHero.title": [
    {
      "type": 0,
      "value": "Экосистема"
    }
  ],
  "components.ergoExplorer.button1": [
    {
      "type": 0,
      "value": "ИССЛЕДОВАТЕЛЬ"
    }
  ],
  "components.ergoExplorer.button2": [
    {
      "type": 0,
      "value": "ERGO.WATCH"
    }
  ],
  "components.ergoRaffle.description": [
    {
      "type": 0,
      "value": "ErgoRaffle is a crowdfunding service built on Ergo Platform that enables anyone to raise money for a project. This project can range from a direct donation to a charity, an academic or business plan, or anything you can convince people to part with their hard-earned ERG for! As an added bonus, after finishing the Raffle, a lottery takes place, and one lucky participant wins a set percent of the Raffle as a \"raffle reward\"."
    }
  ],
  "components.ergoRaffle.heading": [
    {
      "type": 0,
      "value": "Ergo Raffle"
    }
  ],
  "components.ergofoundation.list1": [
    {
      "type": 0,
      "value": "Содействие "
    },
    {
      "children": [
        {
          "type": 0,
          "value": "непрерывной разработке "
        }
      ],
      "type": 8,
      "value": "b"
    },
    {
      "type": 0,
      "value": " протокола платформы Ergo;"
    }
  ],
  "components.ergofoundation.list2": [
    {
      "type": 0,
      "value": "Информирование о широком внедрении и использовании платформы Ergo и ее "
    },
    {
      "children": [
        {
          "type": 0,
          "value": " нативного токена "
        }
      ],
      "type": 8,
      "value": "b"
    },
    {
      "type": 0,
      "value": " (ERG);"
    }
  ],
  "components.ergofoundation.list3": [
    {
      "type": 0,
      "value": "Развитие "
    },
    {
      "children": [
        {
          "type": 0,
          "value": "экосистемы "
        }
      ],
      "type": 8,
      "value": "b"
    },
    {
      "type": 0,
      "value": " вокруг платформы Ergo;"
    }
  ],
  "components.ergofoundation.list4": [
    {
      "type": 0,
      "value": "Распространять использование платформы Ergo и технологии блокчейн для "
    },
    {
      "children": [
        {
          "type": 0,
          "value": " общественного блага "
        }
      ],
      "type": 8,
      "value": "b"
    },
    {
      "type": 0,
      "value": " ;"
    }
  ],
  "components.ergofoundation.list5": [
    {
      "type": 0,
      "value": "Поддерживать "
    },
    {
      "children": [
        {
          "type": 0,
          "value": "действительно децентрализованную инфраструктуру"
        }
      ],
      "type": 8,
      "value": "b"
    },
    {
      "type": 0,
      "value": " и;"
    }
  ],
  "components.ergofoundation.list6": [
    {
      "type": 0,
      "value": "Поддерживать "
    },
    {
      "children": [
        {
          "type": 0,
          "value": "неприкосновенность частной жизни "
        }
      ],
      "type": 8,
      "value": "b"
    },
    {
      "type": 0,
      "value": " как основного права человека."
    }
  ],
  "components.ergofoundation.title": [
    {
      "children": [
        {
          "type": 0,
          "value": "Фонд Ergo"
        }
      ],
      "type": 8,
      "value": "b"
    },
    {
      "type": 0,
      "value": " – это общественная организация, ориентированная на:"
    }
  ],
  "components.exchanges.available": [
    {
      "type": 0,
      "value": "Доступно на популярных централизованных и децентрализованных биржах."
    }
  ],
  "components.exchanges.disclaimer": [
    {
      "type": 0,
      "value": "Отказ от ответственности: биржи предоставляют сильно отличающийся уровень безопасности, защиты конфиденциальности и контроля над вашими средствами и информацией. Мы настоятельно рекомендуем управлять своими собственными средствами и использовать один из предоставленных выше вариантов кошельков."
    }
  ],
  "components.exchanges.heading": [
    {
      "type": 0,
      "value": "ПОКУПАЙТЕ, ПРОДАВАЙТЕ И ТОРГУЙТЕ ERGO"
    }
  ],
  "components.exchanges.subheading": [
    {
      "type": 0,
      "value": "Биржи"
    }
  ],
  "components.explore.description": [
    {
      "type": 0,
      "value": "Ergo Explorer - это ваш интерфейс с блокчейном. Следите за каждой сделкой в реальном времени. Или просматривайте метрики, подобранные сообществом на ergo.watch."
    }
  ],
  "components.explore.heading": [
    {
      "type": 0,
      "value": "Исследуйте"
    }
  ],
  "components.explore.subheading": [
    {
      "type": 0,
      "value": "ОКУНИТЕСЬ В МОРЕ ТРАНЗАКЦИЙ ERGO"
    }
  ],
  "components.faq.anyQuestions": [
    {
      "type": 0,
      "value": "ЕСТЬ ВОПРОСЫ?"
    }
  ],
  "components.faq.description": [
    {
      "type": 0,
      "value": "Мы собрали наиболее часто задаваемые вопросы."
    }
  ],
  "components.faq.heading": [
    {
      "type": 0,
      "value": "Часто задаваемые вопросы"
    }
  ],
  "components.faq.text.2": [
    {
      "type": 0,
      "value": "НЕ МОЖЕТЕ НАЙТИ ТО, "
    },
    {
      "type": 1,
      "value": "breakingLine"
    },
    {
      "type": 0,
      "value": " ЧТО ИЩЕТЕ?"
    }
  ],
  "components.favorites.button1": [
    {
      "type": 0,
      "value": "УЗНАТЬ ОБ ERGO RAFFLE"
    }
  ],
  "components.getErg.BuyIt.text": [
    {
      "type": 0,
      "value": "Доступно на популярных централизованных и децентрализованных биржах."
    }
  ],
  "components.getErg.BuyIt.title": [
    {
      "type": 0,
      "value": "Биржи"
    }
  ],
  "components.getErg.MineIt.text": [
    {
      "type": 0,
      "value": "Autolykos - алгоритм ASIC-resistant и справедливой добычи Proof-of-Work, дружественный для обычных GPU."
    }
  ],
  "components.getErg.MineIt.title": [
    {
      "type": 0,
      "value": "Добыть"
    }
  ],
  "components.getErg.StoreIt.text": [
    {
      "type": 0,
      "value": "Простые и безопасные некастодиальные кошельки для сохранения ваших ERG."
    }
  ],
  "components.getErg.StoreIt.title": [
    {
      "type": 0,
      "value": "Кошельки"
    }
  ],
  "components.getErg.UseIt.title": [
    {
      "type": 0,
      "value": "Используйте ERG уже сегодня в нашей развивающейся экосистеме."
    }
  ],
  "components.getErg.description": [
    {
      "type": 0,
      "value": "На платформе Ergo развивается богатая экосистема. Мы предлагаем решения для разработчиков, майнеров и инвесторов."
    }
  ],
  "components.getErg.heroTitle": [
    {
      "type": 0,
      "value": "НЕПОБЕДИМЫЙ ДЕЦЕНТРАЛИЗОВАННЫЙ ФИНАНС"
    }
  ],
  "components.getErg.title": [
    {
      "type": 0,
      "value": "Получите ERG"
    }
  ],
  "components.grantsAndBounties.button1": [
    {
      "type": 0,
      "value": "СОТРУДНИЧЕСТВО"
    }
  ],
  "components.grantsAndBounties.button2": [
    {
      "type": 0,
      "value": "НАЧАТЬ RAFFLE"
    }
  ],
  "components.grantsAndBounties.button3": [
    {
      "type": 0,
      "value": "СВЯЗАТЬСЯ"
    }
  ],
  "components.grantsAndBounties.description": [
    {
      "type": 0,
      "value": "В общем, любое обучающее материалы для сообщества подлежит вознаграждению, даже если оно не указано в списке. Мы ищем проекты, направленные на построение ключевой инфраструктуры экосистемы. Однако, самый быстрый способ получить финансирование - это начать розыгрыш."
    }
  ],
  "components.grantsAndBounties.heading": [
    {
      "type": 0,
      "value": "Гранты и вознаграждения"
    }
  ],
  "components.hallOfFame.description1": [
    {
      "type": 0,
      "value": "Ergo была основана командой, которая имеет солидный опыт в разработке основных криптовалют и фреймворков блокчейна, включая NXT, Scorex, Cardano и Waves. Ниже приведены краткие биографии некоторых из основной команды ERGO, а также многих других разработчиков и участников сообщества, некоторые из которых анонимны."
    }
  ],
  "components.hallOfFame.description2": [
    {
      "type": 0,
      "value": "Ergo – это основа, и большинство членов основной команды (и даже членов фонда) начинали как члены сообщества. Внизу этой страницы есть краткое описание, а также информация, чтобы узнать больше о Фонде Эрго."
    }
  ],
  "components.hallOfFame.tab1": [
    {
      "type": 0,
      "value": "ЯДРО"
    }
  ],
  "components.hallOfFame.tab2": [
    {
      "type": 0,
      "value": "СООБЩЕСТВО"
    }
  ],
  "components.hallOfFame.tab3": [
    {
      "type": 0,
      "value": "ФОНД"
    }
  ],
  "components.hallOfFame.title": [
    {
      "type": 0,
      "value": "Зал Славы"
    }
  ],
  "components.highlights.slide.1.quote": [
    {
      "type": 0,
      "value": "95,57% "
    },
    {
      "type": 1,
      "value": "breakingLine"
    },
    {
      "type": 0,
      "value": "Публичное распределение"
    }
  ],
  "components.highlights.slide.1.text": [
    {
      "type": 0,
      "value": "Когда Ergo запустился в 2019 году, не было ни начального предложения монет, ни предварительной добычи, ни предварительного распределения токенов каким-либо членам команды или венчурным капиталистам. Действительно справедливый запуск с 4,43% средств, выделенных на развитие экосистемы. Без прецедента в любой другой платформе смарт-контрактов."
    }
  ],
  "components.highlights.slide.1.title": [
    {
      "type": 0,
      "value": "Справедливый старт"
    }
  ],
  "components.highlights.slide.2.quote": [
    {
      "type": 0,
      "value": "TRUE P2P"
    }
  ],
  "components.highlights.slide.2.text": [
    {
      "type": 0,
      "value": "Позволяя более инновационные, целевые реализации, которые не могут соответствовать традиционному банковскому сектору. Ergo предлагает мощные инструменты с умными контрактами для микрокредитных учреждений и местных торговых систем обмена (LETS)."
    }
  ],
  "components.highlights.slide.2.title": [
    {
      "type": 0,
      "value": "Альтернативная экономика"
    }
  ],
  "components.highlights.slide.3.quote": [
    {
      "type": 0,
      "value": "Σ-protocols"
    }
  ],
  "components.highlights.slide.3.text": [
    {
      "type": 0,
      "value": "Конфиденциальность должна оставаться вариантом для защиты автономии. Конфиденциальность - это возможность создания барьеров и установки границ для создания пространства для индивидуальности. Каждый сам выбирает границы и ограничения, которые он хочет создать. Это позволяет новым моделям финансового взаимодействия, основанным на безопасном и богатом языке сценариев ErgoScript и гибких и мощных доказательствах нулевого знания."
    }
  ],
  "components.highlights.slide.3.title": [
    {
      "type": 0,
      "value": "Дополнительная конфиденциальность"
    }
  ],
  "components.highlights.title": [
    {
      "type": 0,
      "value": "Главное"
    }
  ],
  "components.homeHero.button": [
    {
      "type": 0,
      "value": "УЗНАТЬ БОЛЬШЕ"
    }
  ],
  "components.homeHero.text": [
    {
      "type": 0,
      "value": "Ergo — это платформа смарт-контрактов нового поколения, которая обеспечивает экономическую свободу обычных людей с помощью безопасных, доступных и децентрализованных финансовых инструментов."
    }
  ],
  "components.homeHero.title": [
    {
      "type": 0,
      "value": "Обеспечение финансовой системы будущего"
    }
  ],
  "components.homeInfo.blockReward": [
    {
      "type": 0,
      "value": "НАГРАДА ЗА БЛОК"
    }
  ],
  "components.homeInfo.circulatingSupply": [
    {
      "type": 0,
      "value": "ОБЪЕМ В ОБРАЩЕНИИ"
    }
  ],
  "components.homeInfo.hashRate": [
    {
      "type": 0,
      "value": "МОЩНОСТЬ СЕТИ"
    }
  ],
  "components.homeInfo.transactionPerDay": [
    {
      "type": 0,
      "value": "ТРАНЗАКЦИЙ В ДЕНЬ"
    }
  ],
  "components.learn.description": [
    {
      "type": 0,
      "value": "Начните с основ. Что такое Ergo? Что вы можете делать на Ergo?"
    }
  ],
  "components.learn.heading": [
    {
      "type": 0,
      "value": "Учиться"
    }
  ],
  "components.mining.button1": [
    {
      "type": 0,
      "value": "ДОКУМЕНТАЦИЯ"
    }
  ],
  "components.mining.button2": [
    {
      "type": 0,
      "value": "СТАТИСТИКА ПУЛА ДЛЯ МАЙНИНГА"
    }
  ],
  "components.mining.button3": [
    {
      "type": 0,
      "value": "DISCORD"
    }
  ],
  "components.mining.button4": [
    {
      "type": 0,
      "value": "SUBREDDIT"
    }
  ],
  "components.mining.button5": [
    {
      "type": 0,
      "value": "ПОСТЫ БЛОГА О МАЙНИНГЕ"
    }
  ],
  "components.mining.calculator.currentBlockReward": [
    {
      "type": 0,
      "value": "Текущая награда за блок"
    }
  ],
  "components.mining.calculator.currentPrice": [
    {
      "type": 0,
      "value": "Текущая цена"
    }
  ],
  "components.mining.calculator.description": [
    {
      "type": 0,
      "value": "Autolykos - это алгоритм, ориентированный на GPU, основанный на устойчивой к ASIC технологии Proof of Work (PoW) с жестким доступом к памяти."
    }
  ],
  "components.mining.calculator.networkHashrate": [
    {
      "type": 0,
      "value": "Хешрейт сети"
    }
  ],
  "components.mining.calculator.rev": [
    {
      "type": 0,
      "value": "Дневной доход"
    }
  ],
  "components.mining.calculator.title": [
    {
      "type": 0,
      "value": "Калькулятор майнинга"
    }
  ],
  "components.mining.minersTitle": [
    {
      "type": 0,
      "value": "Майнеры"
    }
  ],
  "components.mining.miningPoolsTitle": [
    {
      "type": 0,
      "value": "Пулы для майнинга"
    }
  ],
  "components.mining.text.1": [
    {
      "type": 0,
      "value": "Майнинг Ergo основан на алгоритме «Autolykos», основанном на принципе «Доказательтве выполнения работы» (Proof of Work), устойчивом к ASIC. Майнеры могут настраивать параметры с помощью голосования в сети, а более крупные изменения вносятся квалифицированным большинством с помощью софт-форка. А также можно участвовать в любых захватывающих разработках, таких как токены для голосования, под-пулы и майнинг пространства журналов. Ergo фокусируется на простоте в ядре, с расширенными функциями, построенными на прикладном уровне, для создания устойчивых договорных денег."
    }
  ],
  "components.mining.text.2": [
    {
      "type": 0,
      "value": "Добро пожаловать в будущее принципа «Доказательтво выполнения работы» (Proof of Work)"
    }
  ],
  "components.mining.text.3": [
    {
      "type": 0,
      "value": "Чтобы начать работу, ознакомьтесь с созданным сообществом Справочником по майнингу, документацией или присоединитесь к дискуссионным площадкам по майнингу."
    }
  ],
  "components.mining.title": [
    {
      "type": 0,
      "value": "Майнинг"
    }
  ],
  "components.news.blog": [
    {
      "type": 0,
      "value": "Блог"
    }
  ],
  "components.news.latest": [
    {
      "type": 0,
      "value": "Последние новости"
    }
  ],
  "components.news.title": [
    {
      "type": 0,
      "value": "Новости"
    }
  ],
  "components.ourFavorites.heading": [
    {
      "type": 0,
      "value": "НАШИ ИЗБРАННЫЕ"
    }
  ],
  "components.ourmission.description": [
    {
      "type": 0,
      "value": "Фонд Ergo стремится к органичному и непрерывному развитию протокола платформы Ergo."
    }
  ],
  "components.ourmission.emissionAndTokenomics": [
    {
      "type": 0,
      "value": "ЭМИССИЯ И ТОКЕНОМИКА"
    }
  ],
  "components.ourmission.ergofoundation": [
    {
      "type": 0,
      "value": "ФОНД ERGO"
    }
  ],
  "components.ourmission.reachus.twitter": [
    {
      "type": 0,
      "value": "СЛЕДИТЬ ЗА НАМИ В TWITTER"
    }
  ],
  "components.ourmission.subdescription": [
    {
      "type": 0,
      "value": "Фонд Ergo стремится приложить усилия, чтобы максимизировать количество ценных разработок экосистемы, сделанных с открытым исходным кодом с минимально возможной разрешительной лицензией."
    }
  ],
  "components.ourmission.title": [
    {
      "type": 0,
      "value": "Наша Миссия"
    }
  ],
  "components.partners.title": [
    {
      "type": 0,
      "value": "Партнеры"
    }
  ],
  "components.roadmap.coinmarketcal": [
    {
      "type": 0,
      "value": "УЗНАТЬ БОЛЬШЕ НА COINMARKETCAL"
    }
  ],
  "components.roadmap.description": [
    {
      "type": 0,
      "value": "Обратите внимание, что Ergo — это платформа. Многие из перечисленных ниже проектов не имеют формальной связи ни с Фондом Ergo, ни друг с другом."
    }
  ],
  "components.roadmap.section1.title": [
    {
      "type": 0,
      "value": "СДЕЛАНО"
    }
  ],
  "components.roadmap.section2.title": [
    {
      "type": 0,
      "value": "ЭКОСИСТЕМА"
    }
  ],
  "components.roadmap.section3.title": [
    {
      "type": 0,
      "value": "СКОРО"
    }
  ],
  "components.roadmap.section4.title": [
    {
      "type": 0,
      "value": "2024 И ДАЛЕЕ"
    }
  ],
  "components.roadmap.title": [
    {
      "type": 0,
      "value": "Дорожная карта"
    }
  ],
  "components.software.description": [
    {
      "type": 0,
      "value": "Узел Ergo - ваша точка входа для разработки на Ergo и позволяет вам взаимодействовать с блокчейном."
    }
  ],
  "components.software.heading": [
    {
      "type": 0,
      "value": "Программное обеспечение"
    }
  ],
  "components.uniqueErgo.card1.button": [
    {
      "type": 0,
      "value": "ИЗУЧИТЬ"
    }
  ],
  "components.uniqueErgo.card1.text": [
    {
      "type": 0,
      "value": "Ergo опирается на десятилетний опыт разработки блокчейна, дополняя проверенные принципы лучшими рецензируемыми академическими исследованиями в области криптографии, моделей консенсуса и цифровых валют. Мы начинаем с прочных основ блокчейна и изначально реализуем новую и мощную криптографию."
    }
  ],
  "components.uniqueErgo.card1.title": [
    {
      "type": 0,
      "value": "ИССЛЕДОВАНИЯ И ФОКУС НА РЕАЛЬНОМ ПРИМЕНЕНИИ"
    }
  ],
  "components.uniqueErgo.card2.button": [
    {
      "type": 0,
      "value": "ИЗУЧИТЬ"
    }
  ],
  "components.uniqueErgo.card2.text": [
    {
      "type": 0,
      "value": "Ergo обеспечивает превосходную поддержку для реальных финансовых соглашений. Ergo может поддерживать универсальные распределенные приложения (dApps), которые работают предсказуемо, с известными затратами и не несут никаких опасностей неограниченной функциональности. Смарт-контракты Ergo позволяют нам выполнять широкий спектр задач и могут быть Тьюринг-полными, но мы всегда заранее знаем, сколько будет стоить код и будет ли он работать успешно."
    }
  ],
  "components.uniqueErgo.card2.title": [
    {
      "type": 0,
      "value": "МОЩНОСТЬ И БЕЗОПАСНОСТЬ"
    }
  ],
  "components.uniqueErgo.card3.button": [
    {
      "type": 0,
      "value": "ИЗУЧИТЬ"
    }
  ],
  "components.uniqueErgo.card3.text": [
    {
      "type": 0,
      "value": "Сигма-протоколы (Σ-протоколы) являются основой смарт-контрактов Ergo. Они позволяют создать класс эффективных протоколов с нулевым разглашением, которые позволяют нам выполнять сложные задачи, которые в противном случае были бы невозможными, рискованными или дорогостоящими. Добро пожаловать в самостоятельную конфиденциальность на уровне приложений: ненадежные сценарии, которые можно использовать для доступа к микшерам или другим функциям без участия третьих лиц."
    }
  ],
  "components.uniqueErgo.card3.title": [
    {
      "type": 0,
      "value": "ИНТЕЛЛЕКТУАЛЬНОСТЬ И ПРОСТОТА"
    }
  ],
  "components.uniqueErgo.card4.button": [
    {
      "type": 0,
      "value": "ИЗУЧИТЬ"
    }
  ],
  "components.uniqueErgo.card4.text": [
    {
      "type": 0,
      "value": "Обычные пользователи, которые не используют полный узел, должны пользоваться теми же преимуществами безопасности, что и майнеры. Неинтерактивные доказательства работы (NIPOPOWS) позволяют нам совершать и проверять транзакции с полной уверенностью, не требуя хранения, пропускной способности и времени, необходимых для загрузки полной цепочки блоков. Требуется всего 1 МБ данных, что означает, что вы можете использовать любое устройство."
    }
  ],
  "components.uniqueErgo.card4.title": [
    {
      "type": 0,
      "value": "БЕЗОПАСНОСТЬ И ДОСТУПНОСТЬ"
    }
  ],
  "components.uniqueErgo.title": [
    {
      "type": 0,
      "value": "ЧТО ДЕЛАЕТ ERGO УНИКАЛЬНЫМ"
    }
  ],
  "components.usingErg.BuyIt.text": [
    {
      "type": 0,
      "value": "Доступны на популярных централизованных и децентрализованных биржах."
    }
  ],
  "components.usingErg.BuyIt.title": [
    {
      "type": 0,
      "value": "Биржи"
    }
  ],
  "components.usingErg.MineIt.text": [
    {
      "type": 0,
      "value": "Autolykos - алгоритм Proof-of-Work, устойчивый к ASIC, дружественный к обычным GPU и честно добытый."
    }
  ],
  "components.usingErg.MineIt.title": [
    {
      "type": 0,
      "value": "Майнинг"
    }
  ],
  "components.usingErg.StoreIt.text": [
    {
      "type": 0,
      "value": "Простые и безопасные некастодиальные кошельки для сохранения ваших ERG."
    }
  ],
  "components.usingErg.StoreIt.title": [
    {
      "type": 0,
      "value": "Кошельки"
    }
  ],
  "components.usingErg.UseIt.title": [
    {
      "type": 0,
      "value": "Используйте ERG уже сегодня в нашей развивающейся экосистеме."
    }
  ],
  "components.usingErg.description": [
    {
      "type": 0,
      "value": "На основе Ergo создается продвинутая эко-система. Независимо от того, являетесь ли вы разработчиком, майнером или инвестором – вы получите все возможности"
    }
  ],
  "components.usingErg.subtitle": [
    {
      "type": 0,
      "value": "НЕУДЕРЖИМЫЕ РАСПРЕДЕЛЕННЫЕ ФИНАНСЫ (DEFI)"
    }
  ],
  "components.usingErg.title": [
    {
      "type": 0,
      "value": "ПОЛУЧИТЬ ERG"
    }
  ],
  "components.wallets.chooseYours": [
    {
      "type": 0,
      "value": "ВЫБЕРИТЕ СВОЙ"
    }
  ],
  "components.wallets.coldStorageHeader": [
    {
      "type": 0,
      "value": "Холодное хранилище"
    }
  ],
  "components.wallets.featureHeader": [
    {
      "type": 0,
      "value": "Особенности"
    }
  ],
  "components.wallets.hotStorageHeader": [
    {
      "type": 0,
      "value": "Горячее хранилище"
    }
  ],
  "components.wallets.mobileAppHeader": [
    {
      "type": 0,
      "value": "Мобильное приложение"
    }
  ],
  "components.wallets.setupGuides": [
    {
      "type": 0,
      "value": "ИНСТРУКЦИИ ПО НАСТРОЙКЕ"
    }
  ],
  "components.wallets.walletDescription1": [
    {
      "type": 0,
      "value": "Цифровые кошельки помогают сохранять вашу цифровую валюту в безопасности, обеспечивая конфиденциальность и контроль."
    }
  ],
  "components.wallets.walletDescription2": [
    {
      "type": 0,
      "value": "Обратите внимание, что кошельки поддерживаются третьими лицами, мы предоставляем информацию ниже только как вежливость, чтобы упростить общий опыт работы с цифровыми валютами."
    }
  ],
  "components.wallets.walletsHeader": [
    {
      "type": 0,
      "value": "Кошельки"
    }
  ],
  "components.wallets.walletsTitle": [
    {
      "type": 0,
      "value": "Кошельки"
    }
  ],
  "components.wiki.description": [
    {
      "type": 0,
      "value": "ergonaut.space - это наша общинно-обслуживаемая вики! Забитая полезной информацией о технических подробностях блокчейна Ergo на понятном языке для неспециалистов. Есть также множество руководств, учебников и материалов, предоставленных пользователями. Создайте учетную запись, чтобы начать вносить свой вклад!"
    }
  ],
  "components.wiki.description.short": [
    {
      "type": 0,
      "value": "ergonaut.space - это общинная вики-энциклопедия блокчейна Ergo, переводящая, как использовать и технические подробности Ergo на понятном языке для неспециалистов."
    }
  ],
  "components.wiki.heading": [
    {
      "type": 0,
      "value": "Wiki"
    }
  ],
  "footer.blog.title": [
    {
      "type": 0,
      "value": "БЛОГ"
    }
  ],
  "footer.community.1": [
    {
      "type": 0,
      "value": "Присоединяйтесь к нам"
    }
  ],
  "footer.community.2": [
    {
      "type": 0,
      "value": "Сигманавты"
    }
  ],
  "footer.community.3": [
    {
      "type": 0,
      "value": "Сотрудничество с Ergo"
    }
  ],
  "footer.community.4": [
    {
      "type": 0,
      "value": "Зал СЛавы"
    }
  ],
  "footer.community.5": [
    {
      "type": 0,
      "value": "Фонд Ergo"
    }
  ],
  "footer.community.title": [
    {
      "type": 0,
      "value": "СООБЩЕСТВО"
    }
  ],
  "footer.discover.1": [
    {
      "type": 0,
      "value": "Программное обеспечение"
    }
  ],
  "footer.discover.2": [
    {
      "type": 0,
      "value": "Гранты & Награды"
    }
  ],
  "footer.discover.3": [
    {
      "type": 0,
      "value": "Вопросы и ответы"
    }
  ],
  "footer.discover.4": [
    {
      "type": 0,
      "value": "Исследователь"
    }
  ],
  "footer.discover.5": [
    {
      "type": 0,
      "value": "Документы"
    }
  ],
  "footer.discover.title": [
    {
      "type": 0,
      "value": "ИЗУЧИТЬ"
    }
  ],
  "footer.ecosystem.1": [
    {
      "type": 0,
      "value": "Приложения (DApps)"
    }
  ],
  "footer.ecosystem.2": [
    {
      "type": 0,
      "value": "Дорожная карта"
    }
  ],
  "footer.ecosystem.3": [
    {
      "type": 0,
      "value": "База знаний"
    }
  ],
  "footer.ecosystem.4": [
    {
      "type": 0,
      "value": "Ergo Raffle"
    }
  ],
  "footer.ecosystem.5": [
    {
      "type": 0,
      "value": "Видео-подкасты"
    }
  ],
  "footer.ecosystem.title": [
    {
      "type": 0,
      "value": "ЭКО-СИСТЕМА"
    }
  ],
  "footer.getErg.1": [
    {
      "type": 0,
      "value": "Майнинг"
    }
  ],
  "footer.getErg.2": [
    {
      "type": 0,
      "value": "Калькулятор майнига"
    }
  ],
  "footer.getErg.3": [
    {
      "type": 0,
      "value": "Кошельки"
    }
  ],
  "footer.getErg.4": [
    {
      "type": 0,
      "value": "Биржи"
    }
  ],
  "footer.getErg.title": [
    {
      "type": 0,
      "value": "ПОЛУЧИТЬ ERG"
    }
  ],
  "footer.legal": [
    {
      "type": 0,
      "value": "Законность"
    }
  ],
  "footer.news.title": [
    {
      "type": 0,
      "value": "НОВОСТИ"
    }
  ],
  "footer.privacyPolicy": [
    {
      "type": 0,
      "value": "Политика конфиденциальности"
    }
  ],
  "footer.weGotIt": [
    {
      "type": 0,
      "value": "У нас есть!"
    }
  ],
  "navigation.discover": [
    {
      "type": 0,
      "value": "ИЗУЧИТЬ"
    }
  ],
  "navigation.ecosystem": [
    {
      "type": 0,
      "value": "ЭКО-СИСТЕМА"
    }
  ],
  "navigation.ergoCommunity": [
    {
      "type": 0,
      "value": "ERGO СООБЩЕСТВО"
    }
  ],
  "navigation.getErg": [
    {
      "type": 0,
      "value": "ПОЛУЧИТЬ ERG"
    }
  ],
  "navigation.moreContent": [
    {
      "type": 0,
      "value": "Больше информации?"
    }
  ],
  "pages.404.hero": [
    {
      "type": 0,
      "value": "404. Страница не найдена."
    }
  ],
  "pages.404.title": [
    {
      "type": 0,
      "value": "Не найдено"
    }
  ],
  "pages.blog.title": [
    {
      "type": 0,
      "value": "Блог"
    }
  ],
  "pages.community.title": [
    {
      "type": 0,
      "value": "Сообщество"
    }
  ],
  "pages.discover.title": [
    {
      "type": 0,
      "value": "Изучить"
    }
  ],
  "pages.ecosystem.title": [
    {
      "type": 0,
      "value": "Эко-система"
    }
  ],
  "pages.get-erg.title": [
    {
      "type": 0,
      "value": "Получить ERG"
    }
  ],
  "pages.home.title": [
    {
      "type": 0,
      "value": "Начало"
    }
  ],
  "pages.legal.title": [
    {
      "type": 0,
      "value": "Законность"
    }
  ],
  "pages.mobile-wallets": [
    {
      "type": 0,
      "value": "Мобильные кошельки"
    }
  ],
  "pages.privacyPolicy.title": [
    {
      "type": 0,
      "value": "Политика конфиденциальности"
    }
  ]
}